calc_028/__init__.py
calc_028/calc_028.py
calc_028-0.1.1.dist-info/LICENCE.txt
calc_028-0.1.1.dist-info/METADATA
calc_028-0.1.1.dist-info/WHEEL
calc_028-0.1.1.dist-info/top_level.txt
calc_028-0.1.1.dist-info/RECORD
