Metadata-Version: 2.1
Name: calc-028
Version: 0.1.1
Summary: Calculator program
Author: ibrahim
Author-email: ibrahimkhanalmani@gmail.com
Classifier: Programming Language :: Python :: 3
Classifier: License :: OSI Approved :: MIT License
Classifier: Operating System :: OS Independent
License-File: LICENCE.txt
